madcad/__init__.py
madcad/asso.py
madcad/blending.py
madcad/boolean.py
madcad/common.py
madcad/constraints.py
madcad/core.c
madcad/core.cp39-win_amd64.pyd
madcad/core.pyx
madcad/cut.py
madcad/displays.py
madcad/gear.py
madcad/generation.py
madcad/hashing.py
madcad/hull.py
madcad/io.py
madcad/joints.py
madcad/kinematic.py
madcad/mathutils.py
madcad/mesh.py
madcad/nprint.py
madcad/primitives.py
madcad/rendering.py
madcad/reverse.py
madcad/scheme.py
madcad/selection.py
madcad/settings.py
madcad/standard.py
madcad/text.py
madcad/triangulation.py
madcad/mesh/__init__.py
madcad/mesh/container.py
madcad/mesh/conversions.py
madcad/mesh/mesh.py
madcad/mesh/web.py
madcad/mesh/wire.py
madcad/shaders/annotation.frag
madcad/shaders/annotation.vert
madcad/shaders/axis-ident.vert
madcad/shaders/axis.frag
madcad/shaders/axis.vert
madcad/shaders/font.frag
madcad/shaders/font.vert
madcad/shaders/ghost.frag
madcad/shaders/glowenvelope.frag
madcad/shaders/glowenvelope.vert
madcad/shaders/ident.frag
madcad/shaders/object-ident.vert
madcad/shaders/object-item-ident.vert
madcad/shaders/pointhalo-ident.vert
madcad/shaders/pointhalo.frag
madcad/shaders/pointhalo.vert
madcad/shaders/scheme-ghost.frag
madcad/shaders/scheme-ident.frag
madcad/shaders/scheme-uniform.frag
madcad/shaders/scheme.vert
madcad/shaders/simple-solid.frag
madcad/shaders/solid-old.frag
madcad/shaders/solid.frag
madcad/shaders/solid.vert
madcad/shaders/uniformcolor.frag
madcad/shaders/uniformcolor.vert
madcad/shaders/viewgrid.frag
madcad/shaders/viewgrid.vert
madcad/shaders/voxel.frag
madcad/shaders/voxel.vert
madcad/shaders/wire.frag
madcad/shaders/wire.vert
madcad/textures/point.png
madcad/textures/skybox-blue-dense.png
madcad/textures/skybox-blue.png
madcad/textures/skybox-test.png
madcad/textures/skybox-violet-dense.png
madcad/textures/skybox-violet-saturated.png
madcad/textures/skybox-violet.png
madcad/textures/skybox-white.png
madcad/textures/skybox.png
pymadcad-0.13.0.dist-info/COPYING
pymadcad-0.13.0.dist-info/COPYING.LESSER
pymadcad-0.13.0.dist-info/METADATA
pymadcad-0.13.0.dist-info/WHEEL
pymadcad-0.13.0.dist-info/top_level.txt
pymadcad-0.13.0.dist-info/RECORD
