Metadata-Version: 2.1
Name: pymadcad
Version: 0.13.0
Summary: Simple yet powerful CAD (Computer Aided Design) library, written with Python
Home-page: https://github.com/jimy-byerley/pymadcad
Author: Yves Dejonghe
Author-email: jimy.byerley@gmail.com
License: GNU LGPL v3
Keywords: CAD 3D parametric mesh kinematic solid solver part design
Platform: UNKNOWN
Classifier: License :: OSI Approved :: GNU General Public License v3 or later (GPLv3+)
Classifier: Topic :: Scientific/Engineering
Classifier: Development Status :: 3 - Alpha
Classifier: Programming Language :: Python :: 3.8
Classifier: Programming Language :: Python :: 3.9
Classifier: Programming Language :: Python :: 3.10
Classifier: Programming Language :: Python :: Implementation :: CPython
Classifier: License :: OSI Approved :: GNU Lesser General Public License v3 (LGPLv3)
Classifier: Intended Audience :: Science/Research
Classifier: Intended Audience :: Manufacturing
Classifier: Intended Audience :: Education
Classifier: Topic :: Scientific/Engineering
Classifier: Topic :: Scientific/Engineering :: Visualization
Classifier: Environment :: X11 Applications :: Qt
Requires-Python: >=3.8
Requires-Dist: pyglm (>=2.5.5)
Requires-Dist: moderngl (>=5.6)
Requires-Dist: numpy (>=1.1)
Requires-Dist: scipy (>=1.3)
Requires-Dist: PyQt5 (>=5)
Requires-Dist: Pillow (>=5.4)
Requires-Dist: pyyaml (>=5)
Requires-Dist: arrex (>=0.3.1)
Provides-Extra: obj
Requires-Dist: PyWavefront (>=1.3) ; extra == 'obj'
Provides-Extra: ply
Requires-Dist: plyfile (>=0.7) ; extra == 'ply'
Provides-Extra: stl
Requires-Dist: numpy-stl (>=2) ; extra == 'stl'
